python_libarchive.libs/libarchive-f30c7b17.so.19
python_libarchive-4.2.1.dist-info/top_level.txt
python_libarchive-4.2.1.dist-info/LICENSE
python_libarchive-4.2.1.dist-info/METADATA
python_libarchive-4.2.1.dist-info/RECORD
python_libarchive-4.2.1.dist-info/WHEEL
libarchive/zip.py
libarchive/__libarchive.cpython-39-i386-linux-gnu.so
libarchive/__init__.py
libarchive/tar.py
libarchive/_libarchive.py
