Metadata-Version: 2.1
Name: python-libarchive
Version: 4.2.1
Summary: A libarchive wrapper for Python supporting password protection.
Home-page: https://github.com/smartfile/python-libarchive
Author: Vadim Lebedev, Ben Timby, Travis Cunningham, Ryan Johnston, SmartFile
Author-email: tech@smartfile.com
License: BSD-style license
Platform: any
Classifier: Development Status :: 5 - Production/Stable
Classifier: Intended Audience :: Developers
Classifier: Operating System :: OS Independent
Classifier: Programming Language :: C
Classifier: Programming Language :: Python
Classifier: Topic :: System :: Archiving :: Compression
Classifier: Topic :: Software Development :: Libraries :: Python Modules
License-File: LICENSE
